pubmed_fetcher/__init__.py
pubmed_fetcher/cli.py
pubmed_fetcher/core.py
pubmed_fetcher/fetcher.py
pubmed_fetcher/main.py
pubmed_fetcher/pubmed_fetcher.py
pubmed_fetcher/utils.py
pharma_pubmed_fetcher-0.1.1.dist-info/entry_points.txt
pharma_pubmed_fetcher-0.1.1.dist-info/LICENSE
pharma_pubmed_fetcher-0.1.1.dist-info/METADATA
pharma_pubmed_fetcher-0.1.1.dist-info/WHEEL
pharma_pubmed_fetcher-0.1.1.dist-info/RECORD
