Metadata-Version: 2.3
Name: pharma-pubmed-fetcher
Version: 0.1.1
Summary: A Python package to fetch research papers from PubMed based on user-defined queries
License: MIT
Keywords: PubMed,biotech,pharma,research,papers
Author: Prerana Jatti
Author-email: jattiprerana@gmail.com
Requires-Python: >=3.10,<4.0
Classifier: License :: OSI Approved :: MIT License
Classifier: Programming Language :: Python :: 3
Classifier: Programming Language :: Python :: 3.10
Classifier: Programming Language :: Python :: 3.11
Classifier: Programming Language :: Python :: 3.12
Classifier: Programming Language :: Python :: 3.13
Requires-Dist: biopython (>=1.81,<2.0)
Requires-Dist: click (>=8.1.3,<9.0.0)
Requires-Dist: pandas (>=2.0.0,<3.0.0)
Requires-Dist: requests (>=2.31.0,<3.0.0)
Project-URL: Homepage, https://github.com/Prerana-03/pharma-pubmed-fetcher
Project-URL: Issue Tracker, https://github.com/Prerana-03/pharma-pubmed-fetcher/issues
Project-URL: Repository, https://github.com/Prerana-03/pharma-pubmed-fetcher
